__init__.py
gridmind/__init__.py
gridmind/algorithms/__init__.py
gridmind/algorithms/base_learning_algorithm.py
gridmind/algorithms/evolutionary_rl/__init__.py
gridmind/algorithms/evolutionary_rl/base_evo_rl_algorithm.py
gridmind/algorithms/evolutionary_rl/neuroevolution/__init__.py
gridmind/algorithms/evolutionary_rl/neuroevolution/neuro_agent.py
gridmind/algorithms/evolutionary_rl/neuroevolution/neuroevolution.py
gridmind/algorithms/evolutionary_rl/neuroevolution/neuroevolution_util.py
gridmind/algorithms/function_approximation/__init__.py
gridmind/algorithms/function_approximation/base_function_approximation_based_learning_algorithm.py
gridmind/algorithms/function_approximation/actor_critic/__init__.py
gridmind/algorithms/function_approximation/actor_critic/one_step_actor_critic.py
gridmind/algorithms/function_approximation/monte_carlo/__init__.py
gridmind/algorithms/function_approximation/monte_carlo/control/__init__.py
gridmind/algorithms/function_approximation/monte_carlo/control/reinforce.py
gridmind/algorithms/function_approximation/monte_carlo/control/reinforce_with_baseline.py
gridmind/algorithms/function_approximation/monte_carlo/prediction/__init__.py
gridmind/algorithms/function_approximation/monte_carlo/prediction/gradient_monte_carlo_prediction.py
gridmind/algorithms/function_approximation/ppo/__init__.py
gridmind/algorithms/function_approximation/ppo/ppo.py
gridmind/algorithms/function_approximation/temporal_difference/__init__.py
gridmind/algorithms/function_approximation/temporal_difference/control/__init__.py
gridmind/algorithms/function_approximation/temporal_difference/control/deep_q_learning.py
gridmind/algorithms/function_approximation/temporal_difference/control/episodic_semi_gradient_sarsa.py
gridmind/algorithms/function_approximation/temporal_difference/prediction/__init__.py
gridmind/algorithms/function_approximation/temporal_difference/prediction/semi_gradient_td_0_prediction.py
gridmind/algorithms/tabular/__init__.py
gridmind-0.0.7.dist-info/licenses/LICENSE
gridmind-0.0.7.dist-info/METADATA
gridmind-0.0.7.dist-info/WHEEL
gridmind-0.0.7.dist-info/top_level.txt
gridmind-0.0.7.dist-info/RECORD
