Metadata-Version: 2.4
Name: gridmind
Version: 0.0.7
Author: Falguni Das Shuvo
License: MIT License
Project-URL: Repository, https://github.com/shuvoxcd01/GridMind.git
Keywords: Reinforcement Learning,Temporal Difference,TD Control,TD Prediction,SARSA,Q-Learning,Monte Carlo,Monte Carlo Control,Monte Carlo Prediction,N-Step Methods,N-Step SARSA,N-Step TD
Requires-Python: >=3.10
License-File: LICENSE
Requires-Dist: gymnasium==1.0.0
Requires-Dist: matplotlib==3.7.5
Requires-Dist: numpy==1.24.4
Requires-Dist: tqdm>=4.66.5
Requires-Dist: dill==0.3.8
Requires-Dist: tabulate==0.9.0
Requires-Dist: urllib3>=2.6.0
Requires-Dist: filelock>=3.20.1
Provides-Extra: examples
Requires-Dist: gymnasium[toy-text]==1.0.0; extra == "examples"
Requires-Dist: rl-worlds==0.0.3.post1; extra == "examples"
Provides-Extra: fun-app
Requires-Dist: torch==2.4.1; extra == "fun-app"
Requires-Dist: torchinfo==1.8.0; extra == "fun-app"
Provides-Extra: all
Requires-Dist: torch==2.4.1; extra == "all"
Requires-Dist: torchinfo==1.8.0; extra == "all"
Requires-Dist: gymnasium[toy-text]==1.0.0; extra == "all"
Requires-Dist: gymnasium[box2d]==1.0.0; extra == "all"
Requires-Dist: rl-worlds==0.0.3.post1; extra == "all"
Dynamic: license-file
